README.md
setup.py
bin/genfire
genfire/__init__.py
genfire/fileio.py
genfire/main.py
genfire/reconstruct.py
genfire/utility.py
genfire.egg-info/PKG-INFO
genfire.egg-info/SOURCES.txt
genfire.egg-info/dependency_links.txt
genfire.egg-info/requires.txt
genfire.egg-info/top_level.txt
genfire/gui/CalculateProjectionSeries_Dialog.py
genfire/gui/GENFIRE_MainWindow.py
genfire/gui/GENFIRE_qrc.py
genfire/gui/GENFIRE_qrc_py3.py
genfire/gui/ProjectionCalculator.py
genfire/gui/ProjectionCalculator_MainWindow.py
genfire/gui/VolumeSlicer.py
genfire/gui/VolumeSlicer_MainWindow.py
genfire/gui/__init__.py
genfire/gui/launch.py
genfire/gui/utility.py