Metadata-Version: 1.0
Name: genfire
Version: 1.0.5
Summary: GENeralized Fourier Iterative REconstruction
Home-page: UNKNOWN
Author: Alan (AJ) Pryor, Jr.
Author-email: apryor6@gmail.com
License: UNKNOWN
Platform: UNKNOWN
